sphinxcontrib_autodocgen/__init__.py
sphinx_autodocgen-1.3.dist-info/LICENSE
sphinx_autodocgen-1.3.dist-info/METADATA
sphinx_autodocgen-1.3.dist-info/README.rst
sphinx_autodocgen-1.3.dist-info/WHEEL
sphinx_autodocgen-1.3.dist-info/top_level.txt
sphinx_autodocgen-1.3.dist-info/RECORD
