Metadata-Version: 2.1
Name: sphinx-autodocgen
Version: 1.3
Summary: Sphinx AutoDocGen extension
Home-page: https://github.com/ben-spiller/sphinx-autodocgen
Author: Ben Spiller
Maintainer: Ben Spiller
License: MIT
Project-URL: Repository, https://github.com/ben-spiller/sphinx-autodocgen
Keywords: sphinx,autodoc
Platform: Operating System :: OS Independent
Classifier: License :: OSI Approved :: MIT License
Classifier: Development Status :: 5 - Production/Stable
Classifier: Intended Audience :: Developers
Classifier: Framework :: Sphinx :: Extension
Classifier: Programming Language :: Python :: Implementation :: CPython
Classifier: Intended Audience :: Developers
Classifier: Natural Language :: English
Classifier: Operating System :: OS Independent
Requires-Python: >=3.6, <4
Requires-Dist: sphinx
